{
  "stories": {
    "BT-001": {
      "title": "Apply/restore roundtrip leaves target byte-identical",
      "status": "completed",
      "depends_on": [
        "STORY-007",
        "STORY-008"
      ],
      "retry_count": 0,
      "retry_notes": [],
      "worktree_branch": "bt-001-attempt-1",
      "cost": {
        "input_tokens": 132,
        "output_tokens": 2523,
        "cost_usd": 0.529207,
        "model": "sonnet"
      },
      "conflict_files": [],
      "last_error": ""
    },
    "BT-002": {
      "title": "Partial failure does not corrupt target",
      "status": "completed",
      "depends_on": [
        "STORY-006"
      ],
      "retry_count": 0,
      "retry_notes": [],
      "worktree_branch": "bt-002-attempt-1",
      "cost": {
        "input_tokens": 14,
        "output_tokens": 2822,
        "cost_usd": 0.46769399999999994,
        "model": "sonnet"
      },
      "conflict_files": [],
      "last_error": ""
    },
    "BT-003": {
      "title": "`--target` apply works with no TTY",
      "status": "completed",
      "depends_on": [
        "STORY-007"
      ],
      "retry_count": 0,
      "retry_notes": [],
      "worktree_branch": "bt-003-attempt-1",
      "cost": {
        "input_tokens": 23,
        "output_tokens": 5008,
        "cost_usd": 0.7324529999999998,
        "model": "sonnet"
      },
      "conflict_files": [],
      "last_error": ""
    },
    "BT-004": {
      "title": "`validate` rejects malformed bundles with distinct errors",
      "status": "completed",
      "depends_on": [
        "STORY-003"
      ],
      "retry_count": 0,
      "retry_notes": [],
      "worktree_branch": "bt-004-attempt-1",
      "cost": {
        "input_tokens": 28,
        "output_tokens": 3844,
        "cost_usd": 0.9458179999999998,
        "model": "sonnet"
      },
      "conflict_files": [],
      "last_error": ""
    },
    "BT-005": {
      "title": "CLI smoke tests: all five commands exit with expected codes",
      "status": "completed",
      "depends_on": [],
      "retry_count": 0,
      "retry_notes": [],
      "worktree_branch": "bt-005-attempt-1",
      "cost": {
        "input_tokens": 107,
        "output_tokens": 14834,
        "cost_usd": 1.4865815,
        "model": "sonnet"
      },
      "conflict_files": [],
      "last_error": ""
    },
    "STORY-001": {
      "title": "Project scaffold",
      "status": "completed",
      "depends_on": [],
      "retry_count": 0,
      "retry_notes": [],
      "worktree_branch": "story-001-attempt-1",
      "cost": {
        "input_tokens": 43,
        "output_tokens": 7821,
        "cost_usd": 1.3680949999999998,
        "model": "sonnet"
      },
      "conflict_files": [],
      "last_error": ""
    },
    "STORY-002": {
      "title": "Manifest model and parsing",
      "status": "completed",
      "depends_on": [
        "STORY-001"
      ],
      "retry_count": 0,
      "retry_notes": [],
      "worktree_branch": "story-002-attempt-1",
      "cost": {
        "input_tokens": 22,
        "output_tokens": 4930,
        "cost_usd": 0.78215325,
        "model": "sonnet"
      },
      "conflict_files": [],
      "last_error": ""
    },
    "STORY-003": {
      "title": "`loadout validate` command",
      "status": "completed",
      "depends_on": [
        "STORY-002"
      ],
      "retry_count": 0,
      "retry_notes": [],
      "worktree_branch": "story-003-attempt-1",
      "cost": {
        "input_tokens": 31,
        "output_tokens": 14033,
        "cost_usd": 1.7502890000000002,
        "model": "sonnet"
      },
      "conflict_files": [],
      "last_error": ""
    },
    "STORY-004": {
      "title": "State file management",
      "status": "completed",
      "depends_on": [
        "STORY-001"
      ],
      "retry_count": 0,
      "retry_notes": [],
      "worktree_branch": "story-004-attempt-1",
      "cost": {
        "input_tokens": 498,
        "output_tokens": 3267,
        "cost_usd": 0.6579040000000002,
        "model": "sonnet"
      },
      "conflict_files": [],
      "last_error": ""
    },
    "STORY-005": {
      "title": "Backup creation",
      "status": "completed",
      "depends_on": [
        "STORY-001"
      ],
      "retry_count": 0,
      "retry_notes": [],
      "worktree_branch": "story-005-attempt-1",
      "cost": {
        "input_tokens": 17,
        "output_tokens": 3063,
        "cost_usd": 0.4727262499999999,
        "model": "sonnet"
      },
      "conflict_files": [],
      "last_error": ""
    },
    "STORY-006": {
      "title": "Atomic apply (file write engine)",
      "status": "completed",
      "depends_on": [
        "STORY-002",
        "STORY-003"
      ],
      "retry_count": 0,
      "retry_notes": [],
      "worktree_branch": "story-006-attempt-1",
      "cost": {
        "input_tokens": 852,
        "output_tokens": 6602,
        "cost_usd": 1.1611242499999999,
        "model": "sonnet"
      },
      "conflict_files": [],
      "last_error": ""
    },
    "STORY-007": {
      "title": "`loadout apply` command",
      "status": "completed",
      "depends_on": [
        "STORY-003",
        "STORY-004",
        "STORY-005",
        "STORY-006"
      ],
      "retry_count": 0,
      "retry_notes": [],
      "worktree_branch": "story-007-attempt-1",
      "cost": {
        "input_tokens": 2025,
        "output_tokens": 33662,
        "cost_usd": 3.758950499999999,
        "model": "sonnet"
      },
      "conflict_files": [],
      "last_error": ""
    },
    "STORY-008": {
      "title": "`loadout restore` command",
      "status": "completed",
      "depends_on": [
        "STORY-004",
        "STORY-005",
        "STORY-007"
      ],
      "retry_count": 0,
      "retry_notes": [],
      "worktree_branch": "story-008-attempt-1",
      "cost": {
        "input_tokens": 2301,
        "output_tokens": 7143,
        "cost_usd": 1.3475207499999995,
        "model": "sonnet"
      },
      "conflict_files": [],
      "last_error": ""
    },
    "STORY-009": {
      "title": "Secret scanning",
      "status": "completed",
      "depends_on": [
        "STORY-001"
      ],
      "retry_count": 0,
      "retry_notes": [],
      "worktree_branch": "story-009-attempt-1",
      "cost": {
        "input_tokens": 189,
        "output_tokens": 3184,
        "cost_usd": 0.5473675,
        "model": "sonnet"
      },
      "conflict_files": [],
      "last_error": ""
    },
    "STORY-010": {
      "title": "`loadout capture` command",
      "status": "completed",
      "depends_on": [
        "STORY-002",
        "STORY-009"
      ],
      "retry_count": 0,
      "retry_notes": [],
      "worktree_branch": "story-010-attempt-1",
      "cost": {
        "input_tokens": 1819,
        "output_tokens": 32585,
        "cost_usd": 3.73816675,
        "model": "sonnet"
      },
      "conflict_files": [],
      "last_error": ""
    },
    "STORY-011": {
      "title": "`loadout status` command",
      "status": "completed",
      "depends_on": [
        "STORY-004"
      ],
      "retry_count": 0,
      "retry_notes": [],
      "worktree_branch": "story-011-attempt-1",
      "cost": {
        "input_tokens": 27,
        "output_tokens": 6137,
        "cost_usd": 0.9948347499999999,
        "model": "sonnet"
      },
      "conflict_files": [],
      "last_error": ""
    }
  }
}